agent_demo_framework/__init__.py
agent_demo_framework/main.py
agent_demo_framework/agents/__init__.py
agent_demo_framework/agents/agent_factory.py
agent_demo_framework/agents/base_agent.py
agent_demo_framework/agents/conversational_agent.py
agent_demo_framework/agents/healthcare_agent.py
agent_demo_framework/agents/multistep_agent.py
agent_demo_framework/api/__init__.py
agent_demo_framework/api/chat.py
agent_demo_framework/cmdline/__init__.py
agent_demo_framework/cmdline/healthcare_agent_cli.py
agent_demo_framework/core/__init__.py
agent_demo_framework/core/config.py
agent_demo_framework/data/mock_db/appointments.json
agent_demo_framework/data/mock_db/coverage.json
agent_demo_framework/data/mock_db/meds.json
agent_demo_framework/data/mock_db/patients.json
agent_demo_framework/data/policies/README.md
agent_demo_framework/data/policies/controlled_substances.md
agent_demo_framework/data/policies/imaging_services.md
agent_demo_framework/data/policies/visit_type_restrictions.md
agent_demo_framework/db/__init__.py
agent_demo_framework/db/database.py
agent_demo_framework/models/__init__.py
agent_demo_framework/models/models.py
agent_demo_framework/schemas/__init__.py
agent_demo_framework/schemas/schemas.py
agent_demo_framework/schemas/stream.py
agent_demo_framework/tools/healthcare/__init__.py
agent_demo_framework/tools/healthcare/coverage.py
agent_demo_framework/tools/healthcare/meds.py
agent_demo_framework/tools/healthcare/patient.py
agent_demo_framework/tools/healthcare/policy.py
agent_demo_framework/tools/healthcare/scheduling.py
agent_demo_framework/ui/dist/index.html
agent_demo_framework/ui/dist/assets/index-BNZn_VVH.css
agent_demo_framework/ui/dist/assets/index-DlJZIR2k.js
agent_demo_framework/ui/src/App.css
agent_demo_framework/ui/src/App.tsx
agent_demo_framework/ui/src/main.tsx
agent_demo_framework/ui/src/vite-env.d.ts
agent_demo_framework/ui/src/components/ChatInterface.css
agent_demo_framework/ui/src/components/ChatInterface.tsx
agentorchestra_stack-0.1.1.dist-info/METADATA
agentorchestra_stack-0.1.1.dist-info/WHEEL
agentorchestra_stack-0.1.1.dist-info/entry_points.txt
agentorchestra_stack-0.1.1.dist-info/top_level.txt
agentorchestra_stack-0.1.1.dist-info/RECORD
